{
  "version": "7",
  "dialect": "postgresql",
  "entries": [
    {
      "idx": 0,
      "version": "7",
      "when": 1747446572605,
      "tag": "0000_familiar_wilson_fisk",
      "breakpoints": true
    },
    {
      "idx": 1,
      "version": "7",
      "when": 1747450412139,
      "tag": "0001_third_gambit",
      "breakpoints": true
    },
    {
      "idx": 2,
      "version": "7",
      "when": 1747455070606,
      "tag": "0002_dapper_khan",
      "breakpoints": true
    },
    {
      "idx": 3,
      "version": "7",
      "when": 1747459053704,
      "tag": "0003_flawless_sinister_six",
      "breakpoints": true
    }
  ]
}